monomic/__init__.py
monomic/intermediate.py
monomic-1.0.1.dist-info/LICENSE
monomic-1.0.1.dist-info/METADATA
monomic-1.0.1.dist-info/WHEEL
monomic-1.0.1.dist-info/entry_points.txt
monomic-1.0.1.dist-info/top_level.txt
monomic-1.0.1.dist-info/RECORD
